netdimm/README.md
netdimm/__init__.py
netdimm/message.py
netdimm/netdimm.py
netdimm/py.typed
netdimmutils-0.5.4.dist-info/LICENSE
netdimmutils-0.5.4.dist-info/METADATA
netdimmutils-0.5.4.dist-info/WHEEL
netdimmutils-0.5.4.dist-info/top_level.txt
netdimmutils-0.5.4.dist-info/RECORD
