Metadata-Version: 2.1
Name: netdimmutils
Version: 0.5.4
Summary: Code libraries for working with a SEGA Net Dimm
Home-page: https://github.com/DragonMinded/netboot
Author: DragonMinded
Author-email: dragonminded@dragonminded.com
License: Public Domain
Requires-Python: >=3.6
License-File: LICENSE
Requires-Dist: pycryptodome
Requires-Dist: arcadeutils
Requires-Dist: naomiutils
